setup.py
apiautotest/__about__.py
apiautotest/__init__.py
apiautotest/api.py
apiautotest/built_in.py
apiautotest/cli.py
apiautotest/client.py
apiautotest/compat.py
apiautotest/context.py
apiautotest/exceptions.py
apiautotest/loader.py
apiautotest/locusts.py
apiautotest/logger.py
apiautotest/parser.py
apiautotest/report.py
apiautotest/response.py
apiautotest/runner.py
apiautotest/utils.py
apiautotest/validator.py
apiautotest.egg-info/PKG-INFO
apiautotest.egg-info/SOURCES.txt
apiautotest.egg-info/dependency_links.txt
apiautotest.egg-info/entry_points.txt
apiautotest.egg-info/requires.txt
apiautotest.egg-info/top_level.txt
apiautotest/templates/locustfile_template
apiautotest/templates/report_template.html