Metadata-Version: 1.2
Name: apiautotest
Version: 1.2.4
Summary: One-stop solution for HTTP(S) testing.
Home-page: https://github.com/idibmzjm/apiautotest
Author: jimmy.zhangjm
Author-email: 547980561@qq.com
License: GPL
Keywords: HTTP api test requests locust
Platform: UNKNOWN
Classifier: Development Status :: 3 - Alpha
Classifier: Programming Language :: Python :: 2.7
Classifier: Programming Language :: Python :: 3.4
Classifier: Programming Language :: Python :: 3.5
Classifier: Programming Language :: Python :: 3.6
Classifier: Programming Language :: Python :: 3.7
Requires-Python: >=2.7, !=3.0.*, !=3.1.*, !=3.2.*, !=3.3.*, <4
